fasttyper/__init__.py
fasttyper/__main__.py
fasttyper/application.py
fasttyper/buffer.py
fasttyper/cli.py
fasttyper/components.py
fasttyper/config.py
fasttyper/interface.py
fasttyper/listener.py
fasttyper/runner.py
fasttyper/stats.py
fasttyper-2.4.2.dist-info/LICENSE
fasttyper-2.4.2.dist-info/METADATA
fasttyper-2.4.2.dist-info/WHEEL
fasttyper-2.4.2.dist-info/entry_points.txt
fasttyper-2.4.2.dist-info/top_level.txt
fasttyper-2.4.2.dist-info/RECORD
