Metadata-Version: 2.1
Name: fasttyper
Version: 2.4.2
Summary: Minimalistic typing exercise
Home-page: https://github.com/ickyicky/fasttyper
Author: Piotr Domanski
Author-email: pi.domanski@gmail.com
Classifier: Programming Language :: Python :: 3
Classifier: License :: OSI Approved :: GNU General Public License v3 or later (GPLv3+)
Classifier: Operating System :: OS Independent
Requires-Python: >=3.6
License-File: LICENSE
Requires-Dist: readchar
Requires-Dist: requests
Requires-Dist: windows-curses ; sys_platform == "win32" or sys_platform == "cygwin"
